netping_contr/__init__.py
netping_contr/main.py
netping_contr/mixins.py
netping_contr/tests/__init__.py
netping_contr/tests/main_tests.py
netping_contr-0.0.4.dist-info/METADATA
netping_contr-0.0.4.dist-info/WHEEL
netping_contr-0.0.4.dist-info/top_level.txt
netping_contr-0.0.4.dist-info/RECORD
