Metadata-Version: 2.1
Name: netping_contr
Version: 0.0.4
Author: PunchyArchy
Requires-Dist: requests
Requires-Dist: deprecation
